pycroservice/__init__.py
pycroservice/core.py
pycroservice/rsa.py
pycroservice/util.py
pycroservice-0.1.3.dist-info/METADATA
pycroservice-0.1.3.dist-info/WHEEL
pycroservice-0.1.3.dist-info/top_level.txt
pycroservice-0.1.3.dist-info/RECORD
